{
  "version": "5",
  "dialect": "mysql",
  "id": "0851e364-517c-4271-813d-5bb5a7a25ced",
  "prevId": "00000000-0000-0000-0000-000000000000",
  "tables": {
    "branch": {
      "name": "branch",
      "columns": {
        "branch_no": {
          "name": "branch_no",
          "type": "int",
          "primaryKey": false,
          "notNull": true,
          "autoincrement": false
        },
        "no_of_chapters": {
          "name": "no_of_chapters",
          "type": "int",
          "primaryKey": false,
          "notNull": true,
          "autoincrement": false
        },
        "map_name": {
          "name": "map_name",
          "type": "varchar(100)",
          "primaryKey": false,
          "notNull": true,
          "autoincrement": false
        }
      },
      "indexes": {},
      "foreignKeys": {},
      "compositePrimaryKeys": {
        "branch_branch_no": {
          "name": "branch_branch_no",
          "columns": [
            "branch_no"
          ]
        }
      },
      "uniqueConstraints": {}
    },
    "chapter": {
      "name": "chapter",
      "columns": {
        "chapter_no": {
          "name": "chapter_no",
          "type": "int",
          "primaryKey": false,
          "notNull": true,
          "autoincrement": false
        },
        "branch_no": {
          "name": "branch_no",
          "type": "int",
          "primaryKey": false,
          "notNull": true,
          "autoincrement": false
        },
        "no_of_minigames": {
          "name": "no_of_minigames",
          "type": "int",
          "primaryKey": false,
          "notNull": true,
          "autoincrement": false
        }
      },
      "indexes": {},
      "foreignKeys": {
        "chapter_branch_no_branch_branch_no_fk": {
          "name": "chapter_branch_no_branch_branch_no_fk",
          "tableFrom": "chapter",
          "tableTo": "branch",
          "columnsFrom": [
            "branch_no"
          ],
          "columnsTo": [
            "branch_no"
          ],
          "onDelete": "no action",
          "onUpdate": "no action"
        }
      },
      "compositePrimaryKeys": {
        "chapter_chapter_no": {
          "name": "chapter_chapter_no",
          "columns": [
            "chapter_no"
          ]
        },
        "chapter_chapter_no_branch_no_pk": {
          "name": "chapter_chapter_no_branch_no_pk",
          "columns": [
            "chapter_no",
            "branch_no"
          ]
        }
      },
      "uniqueConstraints": {}
    },
    "level": {
      "name": "level",
      "columns": {
        "level_no": {
          "name": "level_no",
          "type": "int",
          "primaryKey": false,
          "notNull": true,
          "autoincrement": false
        },
        "chapter_no": {
          "name": "chapter_no",
          "type": "int",
          "primaryKey": false,
          "notNull": true,
          "autoincrement": false
        },
        "branch_no": {
          "name": "branch_no",
          "type": "int",
          "primaryKey": false,
          "notNull": true,
          "autoincrement": false
        },
        "minigame_name": {
          "name": "minigame_name",
          "type": "varchar(8)",
          "primaryKey": false,
          "notNull": true,
          "autoincrement": false
        },
        "x": {
          "name": "x",
          "type": "int",
          "primaryKey": false,
          "notNull": true,
          "autoincrement": false
        },
        "y": {
          "name": "y",
          "type": "int",
          "primaryKey": false,
          "notNull": true,
          "autoincrement": false
        }
      },
      "indexes": {},
      "foreignKeys": {
        "level_chapter_no_branch_no_chapter_chapter_no_branch_no_fk": {
          "name": "level_chapter_no_branch_no_chapter_chapter_no_branch_no_fk",
          "tableFrom": "level",
          "tableTo": "chapter",
          "columnsFrom": [
            "chapter_no",
            "branch_no"
          ],
          "columnsTo": [
            "chapter_no",
            "branch_no"
          ],
          "onDelete": "no action",
          "onUpdate": "no action"
        }
      },
      "compositePrimaryKeys": {
        "level_level_no_chapter_no_branch_no_pk": {
          "name": "level_level_no_chapter_no_branch_no_pk",
          "columns": [
            "level_no",
            "chapter_no",
            "branch_no"
          ]
        }
      },
      "uniqueConstraints": {
        "level_chapter_no_branch_no_x_y_unique": {
          "name": "level_chapter_no_branch_no_x_y_unique",
          "columns": [
            "chapter_no",
            "branch_no",
            "x",
            "y"
          ]
        }
      }
    },
    "user": {
      "name": "user",
      "columns": {
        "id": {
          "name": "id",
          "type": "serial",
          "primaryKey": false,
          "notNull": true,
          "autoincrement": true
        },
        "username": {
          "name": "username",
          "type": "varchar(50)",
          "primaryKey": false,
          "notNull": true,
          "autoincrement": false
        },
        "password_hash": {
          "name": "password_hash",
          "type": "varchar(100)",
          "primaryKey": false,
          "notNull": true,
          "autoincrement": false
        },
        "curr_branch_no": {
          "name": "curr_branch_no",
          "type": "int",
          "primaryKey": false,
          "notNull": false,
          "autoincrement": false,
          "default": 1
        },
        "curr_chapter_no": {
          "name": "curr_chapter_no",
          "type": "int",
          "primaryKey": false,
          "notNull": false,
          "autoincrement": false,
          "default": 1
        },
        "curr_level_no": {
          "name": "curr_level_no",
          "type": "int",
          "primaryKey": false,
          "notNull": false,
          "autoincrement": false,
          "default": 1
        }
      },
      "indexes": {},
      "foreignKeys": {},
      "compositePrimaryKeys": {
        "user_id": {
          "name": "user_id",
          "columns": [
            "id"
          ]
        }
      },
      "uniqueConstraints": {
        "user_username_unique": {
          "name": "user_username_unique",
          "columns": [
            "username"
          ]
        }
      }
    },
    "user_session": {
      "name": "user_session",
      "columns": {
        "id": {
          "name": "id",
          "type": "serial",
          "primaryKey": false,
          "notNull": true,
          "autoincrement": true
        },
        "expires_at": {
          "name": "expires_at",
          "type": "datetime",
          "primaryKey": false,
          "notNull": true,
          "autoincrement": false
        },
        "user_id": {
          "name": "user_id",
          "type": "bigint",
          "primaryKey": false,
          "notNull": false,
          "autoincrement": false
        }
      },
      "indexes": {},
      "foreignKeys": {
        "user_session_user_id_user_id_fk": {
          "name": "user_session_user_id_user_id_fk",
          "tableFrom": "user_session",
          "tableTo": "user",
          "columnsFrom": [
            "user_id"
          ],
          "columnsTo": [
            "id"
          ],
          "onDelete": "no action",
          "onUpdate": "no action"
        }
      },
      "compositePrimaryKeys": {
        "user_session_id": {
          "name": "user_session_id",
          "columns": [
            "id"
          ]
        }
      },
      "uniqueConstraints": {}
    }
  },
  "_meta": {
    "schemas": {},
    "tables": {},
    "columns": {}
  },
  "internal": {
    "tables": {},
    "indexes": {}
  }
}